{
  "publisherGroups": [
    {
      "id": 1,
      "publishers": 2000,
      "topicPrefix": "usa/ny/brkl/east/",
      "clientIdPrefix": null
    },
    {
      "id": 2,
      "publishers": 2000,
      "topicPrefix": "usa/ny/brkl/west/",
      "clientIdPrefix": null
    },
    {
      "id": 3,
      "publishers": 2000,
      "topicPrefix": "usa/ny/brkl/north/",
      "clientIdPrefix": null
    },
    {
      "id": 4,
      "publishers": 2000,
      "topicPrefix": "usa/ny/brkl/south/",
      "clientIdPrefix": null
    },
    {
      "id": 5,
      "publishers": 2000,
      "topicPrefix": "usa/ny/manh/east/",
      "clientIdPrefix": null
    },
    {
      "id": 6,
      "publishers": 2000,
      "topicPrefix": "usa/ny/manh/west/",
      "clientIdPrefix": null
    },
    {
      "id": 7,
      "publishers": 2000,
      "topicPrefix": "usa/ny/manh/north/",
      "clientIdPrefix": null
    },
    {
      "id": 8,
      "publishers": 2000,
      "topicPrefix": "usa/ny/manh/south/",
      "clientIdPrefix": null
    },
    {
      "id": 9,
      "publishers": 2000,
      "topicPrefix": "usa/ny/qns/east/",
      "clientIdPrefix": null
    },
    {
      "id": 10,
      "publishers": 2000,
      "topicPrefix": "usa/ny/qns/west/",
      "clientIdPrefix": null
    },
    {
      "id": 11,
      "publishers": 2000,
      "topicPrefix": "usa/ny/qns/north/",
      "clientIdPrefix": null
    },
    {
      "id": 12,
      "publishers": 0,
      "topicPrefix": "usa/ny/qns/south/",
      "clientIdPrefix": null
    },
    {
      "id": 13,
      "publishers": 0,
      "topicPrefix": "usa/ny/brx/east/",
      "clientIdPrefix": null
    },
    {
      "id": 14,
      "publishers": 0,
      "topicPrefix": "usa/ny/brx/west/",
      "clientIdPrefix": null
    },
    {
      "id": 15,
      "publishers": 0,
      "topicPrefix": "usa/ny/brx/north/",
      "clientIdPrefix": null
    },
    {
      "id": 16,
      "publishers": 0,
      "topicPrefix": "usa/ny/brx/south/",
      "clientIdPrefix": null
    },
    {
      "id": 17,
      "publishers": 0,
      "topicPrefix": "usa/ny/si/east/",
      "clientIdPrefix": null
    },
    {
      "id": 18,
      "publishers": 0,
      "topicPrefix": "usa/ny/si/west/",
      "clientIdPrefix": null
    },
    {
      "id": 19,
      "publishers": 0,
      "topicPrefix": "usa/ny/si/north/",
      "clientIdPrefix": null
    },
    {
      "id": 20,
      "publishers": 0,
      "topicPrefix": "usa/ny/si/south/",
      "clientIdPrefix": null
    }
  ],
  "subscriberGroups": [
    {
      "id": 1,
      "subscribers": 1,
      "topicFilter": "usa/ny/brkl/east/+",
      "expectedPublisherGroups": [
        1
      ],
      "persistentSessionInfo": {
        "clientType": "APPLICATION"
      },
      "clientIdPrefix": null
    },
    {
      "id": 2,
      "subscribers": 1,
      "topicFilter": "usa/ny/brkl/west/+",
      "expectedPublisherGroups": [
        2
      ],
      "persistentSessionInfo": {
        "clientType": "APPLICATION"
      },
      "clientIdPrefix": null
    },
    {
      "id": 3,
      "subscribers": 1,
      "topicFilter": "usa/ny/brkl/north/+",
      "expectedPublisherGroups": [
        3
      ],
      "persistentSessionInfo": {
        "clientType": "APPLICATION"
      },
      "clientIdPrefix": null
    },
    {
      "id": 4,
      "subscribers": 1,
      "topicFilter": "usa/ny/brkl/south/+",
      "expectedPublisherGroups": [
        4
      ],
      "persistentSessionInfo": {
        "clientType": "APPLICATION"
      },
      "clientIdPrefix": null
    },
    {
      "id": 5,
      "subscribers": 1,
      "topicFilter": "usa/ny/manh/east/+",
      "expectedPublisherGroups": [
        5
      ],
      "persistentSessionInfo": {
        "clientType": "APPLICATION"
      },
      "clientIdPrefix": null
    },
    {
      "id": 6,
      "subscribers": 1,
      "topicFilter": "usa/ny/manh/west/+",
      "expectedPublisherGroups": [
        6
      ],
      "persistentSessionInfo": {
        "clientType": "APPLICATION"
      },
      "clientIdPrefix": null
    },
    {
      "id": 7,
      "subscribers": 1,
      "topicFilter": "usa/ny/manh/north/+",
      "expectedPublisherGroups": [
        7
      ],
      "persistentSessionInfo": {
        "clientType": "APPLICATION"
      },
      "clientIdPrefix": null
    },
    {
      "id": 8,
      "subscribers": 1,
      "topicFilter": "usa/ny/manh/south/+",
      "expectedPublisherGroups": [
        8
      ],
      "persistentSessionInfo": {
        "clientType": "APPLICATION"
      },
      "clientIdPrefix": null
    },
    {
      "id": 9,
      "subscribers": 1,
      "topicFilter": "usa/ny/qns/east/+",
      "expectedPublisherGroups": [
        9
      ],
      "persistentSessionInfo": {
        "clientType": "APPLICATION"
      },
      "clientIdPrefix": null
    },
    {
      "id": 10,
      "subscribers": 1,
      "topicFilter": "usa/ny/qns/west/+",
      "expectedPublisherGroups": [
        10
      ],
      "persistentSessionInfo": {
        "clientType": "APPLICATION"
      },
      "clientIdPrefix": null
    },
    {
      "id": 11,
      "subscribers": 1,
      "topicFilter": "usa/ny/qns/north/+",
      "expectedPublisherGroups": [
        11
      ],
      "persistentSessionInfo": {
        "clientType": "APPLICATION"
      },
      "clientIdPrefix": null
    },
    {
      "id": 12,
      "subscribers": 0,
      "topicFilter": "usa/ny/qns/south/+",
      "expectedPublisherGroups": [
        12
      ],
      "persistentSessionInfo": {
        "clientType": "APPLICATION"
      },
      "clientIdPrefix": null
    },
    {
      "id": 13,
      "subscribers": 0,
      "topicFilter": "usa/ny/brx/east/+",
      "expectedPublisherGroups": [
        13
      ],
      "persistentSessionInfo": {
        "clientType": "APPLICATION"
      },
      "clientIdPrefix": null
    },
    {
      "id": 14,
      "subscribers": 0,
      "topicFilter": "usa/ny/brx/west/+",
      "expectedPublisherGroups": [
        14
      ],
      "persistentSessionInfo": {
        "clientType": "APPLICATION"
      },
      "clientIdPrefix": null
    },
    {
      "id": 15,
      "subscribers": 0,
      "topicFilter": "usa/ny/brx/north/+",
      "expectedPublisherGroups": [
        15
      ],
      "persistentSessionInfo": {
        "clientType": "APPLICATION"
      },
      "clientIdPrefix": null
    },
    {
      "id": 16,
      "subscribers": 0,
      "topicFilter": "usa/ny/brx/south/+",
      "expectedPublisherGroups": [
        16
      ],
      "persistentSessionInfo": {
        "clientType": "APPLICATION"
      },
      "clientIdPrefix": null
    },
    {
      "id": 17,
      "subscribers": 0,
      "topicFilter": "usa/ny/si/east/+",
      "expectedPublisherGroups": [
        17
      ],
      "persistentSessionInfo": {
        "clientType": "APPLICATION"
      },
      "clientIdPrefix": null
    },
    {
      "id": 18,
      "subscribers": 0,
      "topicFilter": "usa/ny/si/west/+",
      "expectedPublisherGroups": [
        18
      ],
      "persistentSessionInfo": {
        "clientType": "APPLICATION"
      },
      "clientIdPrefix": null
    },
    {
      "id": 19,
      "subscribers": 0,
      "topicFilter": "usa/ny/si/north/+",
      "expectedPublisherGroups": [
        19
      ],
      "persistentSessionInfo": {
        "clientType": "APPLICATION"
      },
      "clientIdPrefix": null
    },
    {
      "id": 20,
      "subscribers": 0,
      "topicFilter": "usa/ny/si/south/+",
      "expectedPublisherGroups": [
        20
      ],
      "persistentSessionInfo": {
        "clientType": "APPLICATION"
      },
      "clientIdPrefix": null
    }
  ],
  "dummyClients": 0,
  "secondsToRun": 300,
  "additionalSecondsToWait": 5,
  "maxMsgsPerPublisherPerSecond": 5,
  "publisherQosValue": 1,
  "subscriberQosValue": 1,
  "minPayloadSize": 1,
  "maxConcurrentOperations": 10000,
  "telemetryKeys": [
    "lat",
    "long",
    "speed",
    "fuel",
    "batLvl"
  ]
}